odoo/addons/sale_order_product_assortment/README.rst
odoo/addons/sale_order_product_assortment/__init__.py
odoo/addons/sale_order_product_assortment/__manifest__.py
odoo/addons/sale_order_product_assortment/i18n/ca.po
odoo/addons/sale_order_product_assortment/i18n/es.po
odoo/addons/sale_order_product_assortment/i18n/it.po
odoo/addons/sale_order_product_assortment/i18n/nl.po
odoo/addons/sale_order_product_assortment/i18n/sale_order_product_assortment.pot
odoo/addons/sale_order_product_assortment/models/__init__.py
odoo/addons/sale_order_product_assortment/models/sale_order.py
odoo/addons/sale_order_product_assortment/readme/CONFIGURE.md
odoo/addons/sale_order_product_assortment/readme/CONTRIBUTORS.md
odoo/addons/sale_order_product_assortment/readme/DESCRIPTION.md
odoo/addons/sale_order_product_assortment/readme/ROADMAP.md
odoo/addons/sale_order_product_assortment/readme/USAGE.md
odoo/addons/sale_order_product_assortment/static/description/icon.png
odoo/addons/sale_order_product_assortment/static/description/index.html
odoo/addons/sale_order_product_assortment/tests/__init__.py
odoo/addons/sale_order_product_assortment/tests/test_sale_order_product_assortment.py
odoo/addons/sale_order_product_assortment/views/sale_order_view.xml
odoo_addon_sale_order_product_assortment-18.0.1.0.0.2.dist-info/METADATA
odoo_addon_sale_order_product_assortment-18.0.1.0.0.2.dist-info/WHEEL
odoo_addon_sale_order_product_assortment-18.0.1.0.0.2.dist-info/top_level.txt
odoo_addon_sale_order_product_assortment-18.0.1.0.0.2.dist-info/RECORD
