Metadata-Version: 2.1
Name: odoo-addon-sale_order_product_assortment
Version: 18.0.1.0.0.2
Requires-Python: >=3.10
Requires-Dist: odoo-addon-base_view_inheritance_extension==18.0.*
Requires-Dist: odoo-addon-product_assortment==18.0.*
Requires-Dist: odoo==18.0.*
Summary: Module that allows to use the assortments on sale orders
Home-page: https://github.com/OCA/sale-workflow
License: AGPL-3
Author: Tecnativa, Odoo Community Association (OCA)
Author-email: support@odoo-community.org
Classifier: Programming Language :: Python
Classifier: Framework :: Odoo
Classifier: Framework :: Odoo :: 18.0
Classifier: License :: OSI Approved :: GNU Affero General Public License v3
Classifier: Development Status :: 4 - Beta
